zoomy_core/__init__.py
zoomy_core/decorators/decorators.py
zoomy_core/fvm/__init__.py
zoomy_core/fvm/flux.py
zoomy_core/fvm/nonconservative_flux.py
zoomy_core/fvm/ode.py
zoomy_core/fvm/solver_numpy.py
zoomy_core/fvm/symbolic_numerics.py
zoomy_core/fvm/timestepping.py
zoomy_core/mesh/__init__.py
zoomy_core/mesh/browse_meshes.py
zoomy_core/mesh/derivatives.py
zoomy_core/mesh/mesh.py
zoomy_core/mesh/mesh_extrude.py
zoomy_core/mesh/mesh_util.py
zoomy_core/mesh/petscmesh.py
zoomy_core/misc/__init__.py
zoomy_core/misc/custom_types.py
zoomy_core/misc/interpolation.py
zoomy_core/misc/io.py
zoomy_core/misc/logger_config.py
zoomy_core/misc/misc.py
zoomy_core/model/__init__.py
zoomy_core/model/analysis.py
zoomy_core/model/basefunction.py
zoomy_core/model/basemodel.py
zoomy_core/model/boundary_conditions.py
zoomy_core/model/initial_conditions.py
zoomy_core/model/model.py
zoomy_core/model/models/GN.py
zoomy_core/model/models/advection.py
zoomy_core/model/models/basisfunctions.py
zoomy_core/model/models/basismatrices.py
zoomy_core/model/models/coupled_constrained.py
zoomy_core/model/models/poisson.py
zoomy_core/model/models/shallow_moments.py
zoomy_core/model/models/shallow_moments_sediment.py
zoomy_core/model/models/shallow_moments_topo.py
zoomy_core/model/models/shallow_moments_variants.py
zoomy_core/model/models/shallow_water.py
zoomy_core/model/models/shallow_water_topo.py
zoomy_core/model/models/shear_shallow_flow.py
zoomy_core/model/models/sme_turbulent.py
zoomy_core/model/models/vam.py
zoomy_core/postprocessing/__init__.py
zoomy_core/postprocessing/plotting.py
zoomy_core/postprocessing/postprocessing.py
zoomy_core/preprocessing/__init__.py
zoomy_core/preprocessing/openfoam_moments.py
zoomy_core/transformation/__init__.py
zoomy_core/transformation/generic_c.py
zoomy_core/transformation/helpers.py
zoomy_core/transformation/to_amrex.py
zoomy_core/transformation/to_c.py
zoomy_core/transformation/to_jax.py
zoomy_core/transformation/to_numpy.py
zoomy_core-0.1.18.dist-info/METADATA
zoomy_core-0.1.18.dist-info/WHEEL
zoomy_core-0.1.18.dist-info/top_level.txt
zoomy_core-0.1.18.dist-info/RECORD
